pedpy/__init__.py
pedpy/_version.py
pedpy/column_identifier.py
pedpy/errors.py
pedpy/data/geometry.py
pedpy/data/trajectory_data.py
pedpy/internal/utils.py
pedpy/io/trajectory_loader.py
pedpy/methods/acceleration_calculator.py
pedpy/methods/density_calculator.py
pedpy/methods/flow_calculator.py
pedpy/methods/method_utils.py
pedpy/methods/profile_calculator.py
pedpy/methods/spatial_analysis.py
pedpy/methods/speed_calculator.py
pedpy/plotting/plotting.py
pedpy-1.4.0.dist-info/licenses/LICENSE
pedpy-1.4.0.dist-info/METADATA
pedpy-1.4.0.dist-info/WHEEL
pedpy-1.4.0.dist-info/top_level.txt
pedpy-1.4.0.dist-info/RECORD
