Metadata-Version: 2.4
Name: PedPy
Version: 1.4.0
Summary: PedPy is a Python module for pedestrian movement analysis.
Author: T. Schrödter
License: MIT License
Project-URL: homepage, https://pedpy.readthedocs.io/
Classifier: Development Status :: 5 - Production/Stable
Classifier: License :: OSI Approved :: MIT License
Classifier: Operating System :: OS Independent
Classifier: Natural Language :: English
Classifier: Programming Language :: Python :: 3 :: Only
Classifier: Programming Language :: Python :: 3
Classifier: Programming Language :: Python :: 3.11
Classifier: Programming Language :: Python :: 3.12
Classifier: Programming Language :: Python :: 3.13
Classifier: Intended Audience :: Developers
Classifier: Intended Audience :: Science/Research
Requires-Python: >=3.11
License-File: LICENSE
Requires-Dist: numpy<3.0,>=2.1
Requires-Dist: pandas<3.0,>=2.2
Requires-Dist: Shapely<3.0,>=2.0
Requires-Dist: scipy<2.0,~=1.15
Requires-Dist: matplotlib<4.0,~=3.10
Requires-Dist: h5py<4.0,~=3.13
Dynamic: license-file
